smsru_api/__init__.py
smsru_api/aioclient.py
smsru_api/client.py
smsru_api/smsru.py
smsru_api/template.py
smsru_api-1.2.dist-info/LICENSE
smsru_api-1.2.dist-info/METADATA
smsru_api-1.2.dist-info/WHEEL
smsru_api-1.2.dist-info/top_level.txt
smsru_api-1.2.dist-info/RECORD
