Metadata-Version: 2.2
Name: smsru_api
Version: 1.2
Summary: [A]sync Python API для сервиса отправки сообщений sms.ru
Home-page: https://github.com/XpycTee/smsru_api
Author: XpycTee
Author-email: i@xpyctee.ru
License: Apache License 2.0
Keywords: async,sync,aio,sms.ru,sms,ru,smsru,sms-verification,verification,sms-messages,messages,api,api-client,http
Classifier: Programming Language :: Python :: 3
Classifier: Programming Language :: Python :: 3.8
Classifier: Programming Language :: Python :: 3.9
Classifier: Programming Language :: Python :: 3.10
Classifier: Programming Language :: Python :: 3.11
Classifier: Programming Language :: Python :: 3.12
Classifier: Programming Language :: Python :: 3.13
Classifier: Programming Language :: Python :: Implementation :: PyPy
Classifier: License :: OSI Approved :: Apache Software License
Classifier: Operating System :: OS Independent
Classifier: Intended Audience :: Developers
Classifier: Topic :: Software Development :: Libraries
Requires-Python: >=3.8
License-File: LICENSE
Requires-Dist: httpx
Dynamic: author
Dynamic: author-email
Dynamic: classifier
Dynamic: description
Dynamic: description-content-type
Dynamic: home-page
Dynamic: keywords
Dynamic: license
Dynamic: requires-dist
Dynamic: requires-python
Dynamic: summary
